vault_monitor/cli.py
vault_monitor-0.4.0.dist-info/METADATA
vault_monitor-0.4.0.dist-info/WHEEL
vault_monitor-0.4.0.dist-info/entry_points.txt
vault_monitor-0.4.0.dist-info/RECORD
